fsvpy/__init__.py
fsvpy/centerline.py
fsvpy/filter.py
fsvpy/locate.py
fsvpy/measure.py
fsvpy/plot.py
fsvpy-1.0.2.dist-info/LICENSE
fsvpy-1.0.2.dist-info/METADATA
fsvpy-1.0.2.dist-info/WHEEL
fsvpy-1.0.2.dist-info/top_level.txt
fsvpy-1.0.2.dist-info/RECORD
