Metadata-Version: 2.1
Name: fsvpy
Version: 1.0.2
Summary: Streak identification and quantification for fluorescent streak velocimetry
Home-page: https://github.com/mmdriscoll/FSVPy
Author: Michelle Driscoll
Author-email: Michelle Driscoll <michelle.driscoll@northwestern.edu>, Jeffrey Richards <jeffrey.richards@northwestern.edu>
License: Copyright (c) 2018 The Python Packaging Authority        
Keywords: feature finding
Classifier: License :: OSI Approved :: MIT License
Classifier: Programming Language :: Python
Classifier: Programming Language :: Python :: 3
License-File: LICENSE
Requires-Dist: pims
Requires-Dist: matplotlib
Requires-Dist: pandas
Requires-Dist: numpy
Requires-Dist: scikit-image
Requires-Dist: networkx
